armory_lib/__init__.py
armory_lib/parsing.py
armory_lib/specific_parsing.py
armory_lib/calcs/__init__.py
armory_lib/calcs/armory_wallet.py
armory_lib/calcs/decryption.py
armory_lib/calcs/hashes.py
armory_lib/calcs/keys.py
armory_lib/types/__init__.py
armory_lib/types/py_btc_address_raw.py
armory_lib/types/py_btc_kdf_params.py
armory_lib/types/py_btc_wallet_raw.py
armory_lib-0.1.2.dist-info/METADATA
armory_lib-0.1.2.dist-info/WHEEL
armory_lib-0.1.2.dist-info/licenses/LICENSE
armory_lib-0.1.2.dist-info/RECORD
